adhoc_api/__init__.py
adhoc_api/curation.py
adhoc_api/data.py
adhoc_api/files.py
adhoc_api/loader.py
adhoc_api/prompts/__init__.py
adhoc_api/prompts/context_free_query.py
adhoc_api/prompts/curator_find_good_matches.py
adhoc_api/prompts/curator_find_perfect_match.py
adhoc_api/prompts/drafter_system.py
adhoc_api/tool.py
adhoc_api/uaii.py
adhoc_api/utils.py
adhoc_api-2.7.0.dist-info/METADATA
adhoc_api-2.7.0.dist-info/WHEEL
adhoc_api-2.7.0.dist-info/RECORD
