Metadata-Version: 2.3
Name: adhoc-api
Version: 2.7.0
Summary: Agent automatically figures out how to make API requests given API docs and user query in plain text
Author: David Samson
Author-email: david.andrew.engineer@gmail.com
Requires-Python: >=3.10,<4.0
Classifier: Programming Language :: Python :: 3
Classifier: Programming Language :: Python :: 3.10
Classifier: Programming Language :: Python :: 3.11
Classifier: Programming Language :: Python :: 3.12
Classifier: Programming Language :: Python :: 3.13
Requires-Dist: anthropic (>=0.49,<1.0)
Requires-Dist: archytas (>=1.4,<2.0)
Requires-Dist: google-genai (>=1.9,<2.0)
Requires-Dist: langchain-google-genai (>=2.1,<3.0)
Requires-Dist: pyyaml (>=6.0,<7.0)
Requires-Dist: requests (>=2.32,<3.0)
Requires-Dist: tiktoken (>=0.8,<0.9)
Requires-Dist: toki (>=0.2,<0.3)
